my_own_package/__init__.py
adela_pack1.0-0.1.0.dist-info/METADATA
adela_pack1.0-0.1.0.dist-info/WHEEL
adela_pack1.0-0.1.0.dist-info/top_level.txt
adela_pack1.0-0.1.0.dist-info/RECORD
