Metadata-Version: 2.1
Name: adela-pack1.0
Version: 0.1.0
Summary: adela my first pack
Home-page: UNKNOWN
Author: adela
Author-email: adela_constantinescu@yahoo.com
License: UNKNOWN
Platform: UNKNOWN
